odoo/addons/account_spread_cost_revenue_enhanced/README.rst
odoo/addons/account_spread_cost_revenue_enhanced/__init__.py
odoo/addons/account_spread_cost_revenue_enhanced/__manifest__.py
odoo/addons/account_spread_cost_revenue_enhanced/i18n/account_spread_cost_revenue_enhanced.pot
odoo/addons/account_spread_cost_revenue_enhanced/i18n/es.po
odoo/addons/account_spread_cost_revenue_enhanced/i18n/it.po
odoo/addons/account_spread_cost_revenue_enhanced/models/__init__.py
odoo/addons/account_spread_cost_revenue_enhanced/models/account_spread.py
odoo/addons/account_spread_cost_revenue_enhanced/models/account_spread_line.py
odoo/addons/account_spread_cost_revenue_enhanced/readme/CONTRIBUTORS.rst
odoo/addons/account_spread_cost_revenue_enhanced/readme/DESCRIPTION.rst
odoo/addons/account_spread_cost_revenue_enhanced/security/ir.model.access.csv
odoo/addons/account_spread_cost_revenue_enhanced/static/description/icon.png
odoo/addons/account_spread_cost_revenue_enhanced/static/description/index.html
odoo/addons/account_spread_cost_revenue_enhanced/views/account_spread.xml
odoo/addons/account_spread_cost_revenue_enhanced/wizards/__init__.py
odoo/addons/account_spread_cost_revenue_enhanced/wizards/account_spread_link_move_line.py
odoo/addons/account_spread_cost_revenue_enhanced/wizards/account_spread_link_move_line.xml
odoo14_addon_account_spread_cost_revenue_enhanced-14.0.1.0.1.dev6.dist-info/METADATA
odoo14_addon_account_spread_cost_revenue_enhanced-14.0.1.0.1.dev6.dist-info/WHEEL
odoo14_addon_account_spread_cost_revenue_enhanced-14.0.1.0.1.dev6.dist-info/top_level.txt
odoo14_addon_account_spread_cost_revenue_enhanced-14.0.1.0.1.dev6.dist-info/RECORD
