Metadata-Version: 2.1
Name: odoo14-addon-account_spread_cost_revenue_enhanced
Version: 14.0.1.0.1.dev6
Summary: Extra feature for account spread cost/revenue
Home-page: https://github.com/OCA/account-financial-tools
Author: Ecosoft,Odoo Community Association (OCA)
Author-email: support@odoo-community.org
License: AGPL-3
Classifier: Programming Language :: Python
Classifier: Framework :: Odoo
Classifier: Framework :: Odoo :: 14.0
Classifier: License :: OSI Approved :: GNU Affero General Public License v3
Classifier: Development Status :: 4 - Beta
Requires-Python: >=3.6
Requires-Dist: odoo14-addon-account-spread-cost-revenue
Requires-Dist: odoo<14.1dev,>=14.0a
